vibeffmpeg/__init__.py
vibeffmpeg/utils.py
vibeffmpeg/app/__init__.py
vibeffmpeg/app/cmd_parser.py
vibeffmpeg/app/wrapper.py
vibeffmpeg/ui/__init__.py
vibeffmpeg/ui/cli.py
vibeffmpeg-0.1.0.dist-info/licenses/LICENSE
vibeffmpeg-0.1.0.dist-info/METADATA
vibeffmpeg-0.1.0.dist-info/WHEEL
vibeffmpeg-0.1.0.dist-info/entry_points.txt
vibeffmpeg-0.1.0.dist-info/top_level.txt
vibeffmpeg-0.1.0.dist-info/RECORD
