Metadata-Version: 2.4
Name: vibeffmpeg
Version: 0.1.0
Summary: FFmpeg made simple. Just type what you want.
Author-email: GintokiSakamoto <GintokiSakamoto@outlook.com>
License: MIT
Classifier: Programming Language :: Python :: 3
Classifier: Operating System :: OS Independent
Requires-Python: >=3.7
License-File: LICENSE
Requires-Dist: rapidfuzz
Dynamic: license-file
